Scrapist/__init__.py
Scrapist/scraper.py
Scrapist/selection.py
Scrapist/soup.py
scrapist-1.0.0.dist-info/LICENSE
scrapist-1.0.0.dist-info/METADATA
scrapist-1.0.0.dist-info/WHEEL
scrapist-1.0.0.dist-info/top_level.txt
scrapist-1.0.0.dist-info/RECORD
