Metadata-Version: 2.1
Name: scrapist
Version: 1.0.0
Summary: A fast web scraper for Python
Home-page: UNKNOWN
Author: Areen-Rath
License: UNKNOWN
Platform: UNKNOWN
Classifier: Programming Language :: Python :: 3
Classifier: License :: OSI Approved :: MIT License
Classifier: Operating System :: OS Independent
Requires-Python: >=3.6
License-File: LICENSE
Requires-Dist: requests
Requires-Dist: beautifulsoup4
Requires-Dist: lxml
